setup.py
c4/junitxml/__init__.py
c4_junitxml.egg-info/PKG-INFO
c4_junitxml.egg-info/SOURCES.txt
c4_junitxml.egg-info/dependency_links.txt
c4_junitxml.egg-info/top_level.txt