Metadata-Version: 1.1
Name: c4-junitxml
Version: 0.0.1
Summary: c4.junitxml
Home-page: UNKNOWN
Author: QA Automation
Author-email: UNKNOWN
License: UNKNOWN
Platform: UNKNOWN
Classifier: Programming Language :: Python :: 3
